kadtk/__init__.py
kadtk/__main__.py
kadtk/emb_loader.py
kadtk/embeds.py
kadtk/fad.py
kadtk/kad.py
kadtk/model_loader.py
kadtk/models/msclap/CLAPWrapper.py
kadtk/models/msclap/__init__.py
kadtk/models/msclap/configs/config_2022.yml
kadtk/models/msclap/configs/config_2023.yml
kadtk/models/msclap/configs/config_clapcap.yml
kadtk/models/msclap/models/__init__.py
kadtk/models/msclap/models/audio.py
kadtk/models/msclap/models/clap.py
kadtk/models/msclap/models/config.py
kadtk/models/msclap/models/htsat.py
kadtk/models/msclap/models/mapper.py
kadtk/models/msclap/models/pytorch_utils.py
kadtk/models/msclap/models/utils.py
kadtk/models/openl3/__init__.py
kadtk/models/openl3/core.py
kadtk/models/openl3/models.py
kadtk/models/openl3/openl3_exceptions.py
kadtk/models/openl3/openl3_warnings.py
kadtk/models/openl3/version.py
kadtk/models/panns/README.md
kadtk/models/panns/__init__.py
kadtk/models/panns/models.py
kadtk/models/panns/pytorch_utils.py
kadtk/utils.py
kadtk-1.1.0.dist-info/LICENSE
kadtk-1.1.0.dist-info/METADATA
kadtk-1.1.0.dist-info/WHEEL
kadtk-1.1.0.dist-info/entry_points.txt
kadtk-1.1.0.dist-info/RECORD
