Metadata-Version: 2.3
Name: kadtk
Version: 1.1.0
Summary: A toolkit library for Kernel Audio Distance.
Author: Yoonjin Chung
Author-email: anazzz1685@gmail.com
Requires-Python: >=3.9,<3.12
Classifier: Programming Language :: Python :: 3
Classifier: Programming Language :: Python :: 3.9
Classifier: Programming Language :: Python :: 3.10
Classifier: Programming Language :: Python :: 3.11
Requires-Dist: encodec (>=0.1.1,<0.2.0)
Requires-Dist: hear21passt (>=0.0.26,<0.0.27)
Requires-Dist: hypy-utils (>=1.0.19,<2.0.0)
Requires-Dist: kapre (>=0.3.5)
Requires-Dist: laion-clap (>=1.1.4,<2.0.0)
Requires-Dist: librosa (>=0.10.1,<0.11.0)
Requires-Dist: nnaudio (>=0.3.2,<0.4.0)
Requires-Dist: numba (>=0.58.0,<0.59.0)
Requires-Dist: numpy (>=1.23.5,<2.0.0)
Requires-Dist: pandas (>=2.0.3,<3.0.0)
Requires-Dist: resampy (>=0.4.2,<0.5.0)
Requires-Dist: scipy (>=1.11.2,<2.0.0)
Requires-Dist: soundfile (>=0.12.1,<0.13.0)
Requires-Dist: tensorflow (>=2.0.0)
Requires-Dist: torch (>=2.1,<2.6)
Requires-Dist: transformers (<4.47.0)
Requires-Dist: wheel (>=0.41.1,<0.42.0)
Project-URL: Homepage, https://github.com/YoonjinXD/kadtk
Project-URL: Repository, https://github.com/YoonjinXD/kadtk
